SRI_Conv/__init__.py
SRI_Conv/sri_cnn.py
SRI_Conv/sri_conv.py
SRI_Conv/sri_resnet.py
SRI_Conv/transforms.py
SRI_Conv/utils.py
SRI_Conv-1.2.5.dist-info/LICENSE
SRI_Conv-1.2.5.dist-info/METADATA
SRI_Conv-1.2.5.dist-info/WHEEL
SRI_Conv-1.2.5.dist-info/top_level.txt
SRI_Conv-1.2.5.dist-info/RECORD
