Metadata-Version: 2.1
Name: SRI_Conv
Version: 1.2.5
Summary: Official package for 'Symmetric Rotation-Invariant Convolutional Kernel'
Author-email: "Yuexi Du, Nicha Dvornek, John Onofrey" <yuexi.du@yale.edu>
Project-URL: Homepage, https://github.com/XYPB/SRI_Conv
Project-URL: Issue, https://github.com/XYPB/SRI_Conv/issues
Classifier: Programming Language :: Python :: 3
Classifier: License :: OSI Approved :: MIT License
Classifier: Operating System :: OS Independent
Requires-Python: >=3.8
License-File: LICENSE
Requires-Dist: scipy >=1.9.0
Requires-Dist: numpy >=1.22.0
Requires-Dist: torch >=1.8.0
